dynamic_unet/__init__.py
dynamic_unet/_nbdev.py
dynamic_unet/core.py
dynamic_unet/decoder.py
dynamic_unet/encoder.py
dynamic_unet/opt.py
dynamic_unet/unet.py
dynamic_unet/utils.py
dynamic_unet-0.0.2.dist-info/LICENSE
dynamic_unet-0.0.2.dist-info/METADATA
dynamic_unet-0.0.2.dist-info/WHEEL
dynamic_unet-0.0.2.dist-info/entry_points.txt
dynamic_unet-0.0.2.dist-info/top_level.txt
dynamic_unet-0.0.2.dist-info/RECORD
